pySAXS/ABOUT.txt
pySAXS/CHANGELOG.txt
pySAXS/LICENSE.txt
pySAXS/__init__.py
pySAXS/createChanges.py
pySAXS/matplotlibwidget.py
pySAXS/startGuiSAXS.py
pySAXS/startGuiSAXSqt.py
pySAXS/LS/LSneutron.py
pySAXS/LS/LSsca.py
pySAXS/LS/LSusaxs.py
pySAXS/LS/SAXSparametersOLD.py
pySAXS/LS/SAXSparametersXML.py
pySAXS/LS/__init__.py
pySAXS/LS/absolute.py
pySAXS/LS/absorption.py
pySAXS/LS/absorptionXRL.py
pySAXS/LS/absorption_utils.py
pySAXS/LS/background.py
pySAXS/LS/invariant.py
pySAXS/LS/rap.py
pySAXS/doc/2011 04 SOP SAXS CEA.pdf
pySAXS/doc/General_theorems_2010.pdf
pySAXS/doc/Initial_data_treatment_2010.pdf
pySAXS/doc/PySaxs at Python for physics.pdf
pySAXS/doc/SAXS USER BASICS.pdf
pySAXS/examples/__init__.py
pySAXS/examples/absoluteScaling.py
pySAXS/examples/absoluteScalingWithoutPredifinedParameters.py
pySAXS/examples/calculateAbsorption.py
pySAXS/examples/calculateAbsorptionXRAYLIB.py
pySAXS/examples/calculateInvariant.py
pySAXS/examples/fitsWithDifferentMethods.py
pySAXS/examples/getFluxFromRPT.py
pySAXS/examples/importDataset.py
pySAXS/examples/openDataAndAbsoluteScale.py
pySAXS/examples/openDisplayEDF.py
pySAXS/examples/openSwingData.py
pySAXS/examples/plottingDataAndFit.py
pySAXS/examples/plottingDataAndFitguiqwt.py
pySAXS/examples/radialAveraging.py
pySAXS/examples/radialAveragingAll.py
pySAXS/examples/readDataFromFilters.py
pySAXS/examples/readRPT.py
pySAXS/examples/simpleRadialAveraging.py
pySAXS/examples/simpleReadData.py
pySAXS/examples/testLMfit.py
pySAXS/examples/testLMfit2.py
pySAXS/filefilters/__init__.py
pySAXS/filefilters/file_type.ini
pySAXS/filefilters/fileimport.py
pySAXS/guisaxs/__init__.py
pySAXS/guisaxs/dataset.py
pySAXS/guisaxs/pySaxsColors.py
pySAXS/guisaxs/images/1356500.svg
pySAXS/guisaxs/images/1356625.svg
pySAXS/guisaxs/images/3214809.svg
pySAXS/guisaxs/images/AutoScale.png
pySAXS/guisaxs/images/CurveStyle.png
pySAXS/guisaxs/images/IQn.png
pySAXS/guisaxs/images/LineStyle.png
pySAXS/guisaxs/images/Logo_UV-vis-Em.png
pySAXS-3.289.dist-info/LICENSE.txt
pySAXS-3.289.dist-info/METADATA
pySAXS-3.289.dist-info/WHEEL
pySAXS-3.289.dist-info/entry_points.txt
pySAXS-3.289.dist-info/top_level.txt
pySAXS-3.289.dist-info/RECORD
