Metadata-Version: 2.1
Name: pySAXS
Version: 3.289
Summary: Python for Small Angle X-ray Scattering data treatment
Home-page: http://iramis.cea.fr/nimbe/lions/
Author: CEA - IRAMIS - LIONS
Author-email: olivier.tache@cea.fr
License: CeCILL
Classifier: Development Status :: 4 - Beta
Classifier: Intended Audience :: Developers
Classifier: Topic :: Software Development :: Build Tools
Classifier: License :: OSI Approved :: MIT License
Classifier: Programming Language :: Python :: 2
Classifier: Programming Language :: Python :: 2.7
Classifier: Programming Language :: Python :: 3
Classifier: Programming Language :: Python :: 3.6
Classifier: Programming Language :: Python :: 3.10
License-File: LICENSE.txt
Requires-Dist: lmfit
Requires-Dist: ConfigParser
Requires-Dist: unidecode
Requires-Dist: weightedstats
Requires-Dist: pyshortcuts
Requires-Dist: pyFAI
Requires-Dist: numba
Requires-Dist: openpyxl
Requires-Dist: PyQt5
Requires-Dist: pandas
Requires-Dist: openpyxl
Requires-Dist: watchdog
